test/__init__.py
test/test_detector.py
test/test_translator.py
xtranslator/__init__.py
xtranslator/detectors/__init__.py
xtranslator/detectors/cld3_detector.py
xtranslator/detectors/detector.py
xtranslator/detectors/fastspell_detector.py
xtranslator/detectors/fasttext_detector.py
xtranslator/detectors/glotlid.py
xtranslator/detectors/google_detector.py
xtranslator/detectors/langdetect_detector.py
xtranslator/detectors/langid_detector.py
xtranslator/detectors/libre_translate.py
xtranslator/detectors/lingua_detector.py
xtranslator/detectors/simplemma_detector.py
xtranslator/detectors/stanza_detector.py
xtranslator/detectors/utils.py
xtranslator/translators/__init__.py
xtranslator/translators/amazon_translator.py
xtranslator/translators/argostranslate.py
xtranslator/translators/deepl_translator.py
xtranslator/translators/google_translator.py
xtranslator/translators/libre_translate.py
xtranslator/translators/m2m100_translator.py
xtranslator/translators/madlad_translator.py
xtranslator/translators/mbart_translator.py
xtranslator/translators/nllb_translator.py
xtranslator/translators/seamless_translator.py
xtranslator/translators/translator.py
xtranslator/translators/utils.py
xtranslator-0.1.0.dist-info/LICENSE
xtranslator-0.1.0.dist-info/METADATA
xtranslator-0.1.0.dist-info/WHEEL
xtranslator-0.1.0.dist-info/top_level.txt
xtranslator-0.1.0.dist-info/RECORD
