Metadata-Version: 2.2
Name: xtranslator
Version: 0.1.0
Summary: A package for translating text and detecting languages
Home-page: https://github.com/ivanvykopal/xtranslator.git
Author: Ivan Vykopal
Author-email: ivan.vykopal@gmail.com
License: MIT
Classifier: Programming Language :: Python :: 3.10
Classifier: License :: OSI Approved :: MIT License
Requires-Python: >=3.10.0
License-File: LICENSE
Requires-Dist: langdetect
Requires-Dist: lingua-language-detector
Requires-Dist: langid
Requires-Dist: stanza
Requires-Dist: fasttext-langdetect
Requires-Dist: simplemma
Requires-Dist: googletrans
Requires-Dist: py-googletrans
Requires-Dist: transformers
Requires-Dist: torch
Requires-Dist: pandas
Requires-Dist: numpy
Requires-Dist: boto3
Requires-Dist: deepl
Requires-Dist: sentencepiece
Requires-Dist: fasttext
Requires-Dist: huggingface_hub
Requires-Dist: argostranslate
Dynamic: author
Dynamic: author-email
Dynamic: classifier
Dynamic: description
Dynamic: description-content-type
Dynamic: home-page
Dynamic: license
Dynamic: requires-dist
Dynamic: requires-python
Dynamic: summary
